{
    "version": 8,
    "configurePresets": [
        {
            "name": "base",
            "hidden": true,
            "generator": "Ninja",
            "binaryDir": "${sourceDir}/build/${presetName}",
            "installDir": "${sourceDir}/install/${presetName}"
        },
        {
            "name": "win-base",
            "hidden": true,
            "inherits": "base",
            "condition": {
                "type": "equals",
                "lhs": "${hostSystemName}",
                "rhs": "Windows"
            },
            "cacheVariables": {
                "CMAKE_C_COMPILER": "cl.exe",
                "CMAKE_CXX_COMPILER": "cl.exe",
                "CMAKE_CXX_FLAGS": "/utf-8 /validate-charset /EHsc /W4",
                "CMAKE_C_FLAGS": "/utf-8 /validate-charset /W4"
            }
        },
        {
            "name": "linux-base",
            "hidden": true,
            "inherits": "base",
            "condition": {
                "type": "equals",
                "lhs": "${hostSystemName}",
                "rhs": "Linux"
            },
            "cacheVariables": {
                "CMAKE_C_COMPILER": "gcc",
                "CMAKE_CXX_COMPILER": "g++",
                "CMAKE_C_FLAGS": "-Wall -Wextra",
                "CMAKE_CXX_FLAGS": "-Wall -Wextra",
                "CMAKE_EXPORT_COMPILE_COMMANDS": true
            }
        },
        {
            "name": "win-debug",
            "inherits": "win-base",
            "displayName": "Windows MSVC Debug",
            "cacheVariables": {
                "CMAKE_BUILD_TYPE": "Debug"
            }
        },
        {
            "name": "win-release",
            "inherits": "win-base",
            "displayName": "Windows MSVC Release",
            "cacheVariables": {
                "CMAKE_BUILD_TYPE": "Release"
            }
        },
        {
            "name": "linux-debug",
            "inherits": "linux-base",
            "displayName": "Linux GCC Debug",
            "cacheVariables": {
                "CMAKE_BUILD_TYPE": "Debug"
            }
        },
        {
            "name": "linux-release",
            "inherits": "linux-base",
            "displayName": "Linux GCC Release",
            "cacheVariables": {
                "CMAKE_BUILD_TYPE": "Release"
            }
        }
    ]
}